py_oathtool2/__init__.py
py_oathtool2/otp.py
py_oathtool2-1.3.0.dist-info/LICENSE
py_oathtool2-1.3.0.dist-info/METADATA
py_oathtool2-1.3.0.dist-info/WHEEL
py_oathtool2-1.3.0.dist-info/entry_points.txt
py_oathtool2-1.3.0.dist-info/top_level.txt
py_oathtool2-1.3.0.dist-info/RECORD
