Metadata-Version: 2.1
Name: py_oathtool2
Version: 1.3.0
Summary: A Python script for generating OTP codes
Author-email: Matthew Taylor <matthew@m-taylor.co.uk>
Project-URL: Homepage, https://github.com/shanet/py_oathtool
Project-URL: Issues, https://github.com/shanet/py_oathtool/issues
Classifier: Intended Audience :: Developers
Classifier: Intended Audience :: System Administrators
Classifier: License :: OSI Approved :: GNU General Public License v2 (GPLv2)
Classifier: Programming Language :: Python :: 3
Classifier: Topic :: Security
Classifier: Topic :: System :: Systems Administration
Classifier: Topic :: Utilities
Requires-Python: >=3.8
License-File: LICENSE
Requires-Dist: oathtool
Requires-Dist: pyaml
